{"id":"crW1gjpkuqgagtSD81a3g","title":"Interviewee","desc":"","updated":1671376224557,"created":1616600289251,"custom":{},"fname":"business.hiring.interviewee","type":"note","vault":{"fsPath":"../main/thoughts-on","name":"thoughts-on"},"contentHash":"1c8b7d8ab8bf3cc8e3be4a01cf9ca1a3","links":[],"anchors":{"as-the-interviewee":{"type":"header","text":"As the Interviewee","value":"as-the-interviewee","line":8,"column":0,"depth":1},"questions":{"type":"header","text":"Questions","value":"questions","line":11,"column":0,"depth":2},"things-to-say":{"type":"header","text":"Things to say","value":"things-to-say","line":20,"column":0,"depth":2},"experience-points":{"type":"header","text":"Experience points","value":"experience-points","line":32,"column":0,"depth":3}},"children":["9NOzZg8odjShrSKIE9GtG"],"parent":"d820ef59-5245-4c89-a4c2-3a0fdeed1cd6","data":{}}
