{"id":"enqduojp3hdl58v8o73g2l8","title":"Compressor","desc":"","updated":1673983141744,"created":1655740012886,"custom":{},"fname":"music.engineering.mixing.compressor","type":"note","vault":{"fsPath":"../main/thoughts-on","name":"thoughts-on"},"contentHash":"9b31518ae3749babbe03b45600469828","links":[{"type":"wiki","from":{"fname":"music.engineering.mixing.compressor","id":"enqduojp3hdl58v8o73g2l8","vaultName":"thoughts-on"},"value":"music.engineering.mixing.EQ","alias":"EQ","position":{"start":{"line":79,"column":59,"offset":5862},"end":{"line":79,"column":93,"offset":5896},"indent":[]},"xvault":false,"sameFile":false,"to":{"fname":"music.engineering.mixing.EQ"}},{"from":{"fname":"music.engineering.mixing.gate","id":"zn9sam5nkf2iipacb540e0q","vaultName":"thoughts-on"},"type":"backlink","position":{"start":{"line":13,"column":23,"offset":1171},"end":{"line":13,"column":113,"offset":1261},"indent":[]},"value":"music.engineering.mixing.compressor"},{"from":{"fname":"music.engineering.mixing.volume","id":"lx0mkvcis0eemrd9nphbm1p","vaultName":"thoughts-on"},"type":"backlink","position":{"start":{"line":9,"column":3,"offset":964},"end":{"line":9,"column":54,"offset":1015},"indent":[]},"value":"music.engineering.mixing.compressor"}],"anchors":{"what-is-it":{"type":"header","text":"What is it?","value":"what-is-it","line":8,"column":0,"depth":2},"flavors-of-compressor":{"type":"header","text":"Flavors of compressor","value":"flavors-of-compressor","line":24,"column":0,"depth":3},"why-use-it":{"type":"header","text":"Why use it?","value":"why-use-it","line":28,"column":0,"depth":2},"better-signal":{"type":"header","text":"Better signal","value":"better-signal","line":33,"column":0,"depth":3},"stabilize-the-sound-image":{"type":"header","text":"Stabilize the sound image","value":"stabilize-the-sound-image","line":36,"column":0,"depth":3},"how-to-use-it":{"type":"header","text":"How to use it?","value":"how-to-use-it","line":45,"column":0,"depth":2},"mix-bus":{"type":"header","text":"Mix Bus","value":"mix-bus","line":48,"column":0,"depth":3},"types-of-compressor":{"type":"header","text":"Types of compressor","value":"types-of-compressor","line":57,"column":0,"depth":2},"expansion":{"type":"header","text":"Expansion","value":"expansion","line":72,"column":0,"depth":3},"compressing-before-or-after-eq":{"type":"header","text":"Compressing before or after EQ","value":"compressing-before-or-after-eq","line":79,"column":0,"depth":3},"where-in-the-fx-chain-to-use-compressor":{"type":"header","text":"Where in the FX chain to use compressor.","value":"where-in-the-fx-chain-to-use-compressor","line":84,"column":0,"depth":3},"ue-resources":{"type":"header","text":"UE Resources","value":"ue-resources","line":91,"column":0,"depth":2}},"children":["2himbbw3l9dpljo03z3vpr5","2ac3ex5vvidpf4v3qdozndp"],"parent":"v89y5ry5pbgeazv7v5jr4me","data":{}}
